README.rst
setup.py
RandOrg.egg-info/PKG-INFO
RandOrg.egg-info/SOURCES.txt
RandOrg.egg-info/dependency_links.txt
RandOrg.egg-info/requires.txt
RandOrg.egg-info/top_level.txt
randomorg/__init__.py
randomorg/_rand_core.py