Metadata-Version: 1.0
Name: RandOrg
Version: 0.1.0
Summary: A Python wrapper to the Random.Org service.
Home-page: https://github.com/asobrien/randomOrg
Author: Anthony O'Brien
Author-email: bftm@permil.org
License: LICENSE.txt
Platform: UNKNOWN
